pytest_keyring/__init__.py
pytest_keyring/pytest_keyring.py
pytest_keyring-1.1.0.dist-info/LICENSE
pytest_keyring-1.1.0.dist-info/METADATA
pytest_keyring-1.1.0.dist-info/WHEEL
pytest_keyring-1.1.0.dist-info/entry_points.txt
pytest_keyring-1.1.0.dist-info/RECORD
