Metadata-Version: 2.1
Name: pytest-keyring
Version: 1.1.0
Summary: A Pytest plugin to access the system's keyring to provide credentials for tests
Home-page: https://github.com/tomasfarias/pytest-keyring
License: MIT
Keywords: keyring,pytest,pytest-plugin
Author: Tomás Farías Santana
Author-email: tomas@tomasfarias.dev
Requires-Python: >=3.8
Classifier: Framework :: Pytest
Classifier: Intended Audience :: Developers
Classifier: License :: OSI Approved :: MIT License
Classifier: Programming Language :: Python :: 3
Classifier: Programming Language :: Python :: 3.8
Classifier: Programming Language :: Python :: 3.9
Classifier: Programming Language :: Python :: 3.10
Classifier: Programming Language :: Python :: 3.11
Classifier: Programming Language :: Python :: 3.12
Requires-Dist: keyring (>=24.2)
Requires-Dist: pytest (>=8.0.2)
Project-URL: Repository, https://github.com/tomasfarias/pytest-keyring
